infera/__init__.py
infera/__main__.py
infera/agent/__init__.py
infera/agent/client.py
infera/agent/hooks.py
infera/agent/interactions.py
infera/agent/mcp.py
infera/agent/prompts.py
infera/agent/prompts/analyze.md
infera/agent/prompts/system.md
infera/agent/prompts/_shared/error_loop.md
infera/agent/prompts/apply/_base.md
infera/agent/prompts/apply/cloudflare.md
infera/agent/prompts/apply/terraform.md
infera/agent/prompts/apply/terraform_dry_run.md
infera/agent/prompts/deploy/_base.md
infera/agent/prompts/destroy/_base.md
infera/agent/prompts/destroy/cloudflare.md
infera/agent/prompts/destroy/terraform.md
infera/agent/prompts/plan/_base.md
infera/agent/prompts/plan/cloudflare.md
infera/agent/prompts/plan/terraform.md
infera/agent/tools/__init__.py
infera/agent/tools/provisioning.py
infera/cli/__init__.py
infera/cli/commands.py
infera/cli/main.py
infera/cli/output.py
infera/core/__init__.py
infera/core/auth.py
infera/core/config.py
infera/core/exceptions.py
infera/core/onboarding.py
infera/core/phases.py
infera/core/preflight.py
infera/core/state.py
infera/templates/__init__.py
infera/templates/_index.md
infera/templates/api_service.md
infera/templates/cloudflare_pages.md
infera/templates/cloudflare_worker.md
infera/templates/containerized.md
infera/templates/fullstack_app.md
infera/templates/static_site.md
infera/templates/aws/amplify_fullstack.md
infera/templates/aws/batch_processing.md
infera/templates/aws/ecs_fargate_api.md
infera/templates/aws/ecs_fargate_fullstack.md
infera/templates/aws/ecs_spot.md
infera/templates/aws/eks_microservices.md
infera/templates/aws/eks_ml_serving.md
infera/templates/aws/elastic_beanstalk.md
infera/templates/aws/eventbridge_lambda.md
infera/templates/aws/lambda_api.md
infera/templates/aws/lambda_sqs.md
infera/templates/aws/multi_region.md
infera/templates/aws/rds_aurora.md
infera/templates/aws/s3_cloudfront.md
infera/templates/aws/step_functions.md
infera/templates/cloudflare/full_stack.md
infera-0.1.1.dist-info/METADATA
infera-0.1.1.dist-info/WHEEL
infera-0.1.1.dist-info/entry_points.txt
infera-0.1.1.dist-info/licenses/LICENSE
infera-0.1.1.dist-info/RECORD
