Metadata-Version: 2.4
Name: infera
Version: 0.1.1
Summary: Agentic infrastructure provisioning from code analysis
Project-URL: Homepage, https://github.com/computer-reinvention/infera
Project-URL: Repository, https://github.com/computer-reinvention/infera
Project-URL: Issues, https://github.com/computer-reinvention/infera/issues
Author: Pankaj Garkoti
License: MIT
License-File: LICENSE
Keywords: agent,ai,aws,azure,cloud,gcp,infrastructure,terraform
Classifier: Development Status :: 3 - Alpha
Classifier: Environment :: Console
Classifier: Intended Audience :: Developers
Classifier: License :: OSI Approved :: MIT License
Classifier: Programming Language :: Python :: 3.11
Classifier: Programming Language :: Python :: 3.12
Classifier: Topic :: Software Development :: Build Tools
Requires-Python: >=3.11
Requires-Dist: claude-agent-sdk>=0.1.0
Requires-Dist: google-auth>=2.25.0
Requires-Dist: google-cloud-billing>=1.13.0
Requires-Dist: google-cloud-run>=0.10.0
Requires-Dist: google-cloud-storage>=2.14.0
Requires-Dist: httpx>=0.26.0
Requires-Dist: pydantic>=2.5.0
Requires-Dist: pyyaml>=6.0
Requires-Dist: rich>=13.0.0
Requires-Dist: typer>=0.9.0
Provides-Extra: dev
Requires-Dist: pyright>=1.1.0; extra == 'dev'
Requires-Dist: pytest-asyncio>=0.23.0; extra == 'dev'
Requires-Dist: pytest-cov>=4.1.0; extra == 'dev'
Requires-Dist: pytest>=7.4.0; extra == 'dev'
Requires-Dist: ruff>=0.1.0; extra == 'dev'
